justcause/__init__.py
justcause/evaluation.py
justcause/metrics.py
justcause/utils.py
justcause/data/__init__.py
justcause/data/frames.py
justcause/data/transport.py
justcause/data/utils.py
justcause/data/generators/__init__.py
justcause/data/generators/ihdp.py
justcause/data/generators/rlearner.py
justcause/data/generators/toy.py
justcause/data/sets/__init__.py
justcause/data/sets/ibm.py
justcause/data/sets/ihdp.py
justcause/data/sets/twins.py
justcause/learners/__init__.py
justcause/learners/propensity.py
justcause/learners/utils.py
justcause/learners/ate/__init__.py
justcause/learners/ate/double_robust.py
justcause/learners/ate/propensity_weighting.py
justcause/learners/meta/__init__.py
justcause/learners/meta/slearner.py
justcause/learners/meta/tlearner.py
JustCause-0.4.dist-info/AUTHORS.rst
JustCause-0.4.dist-info/LICENSE.txt
JustCause-0.4.dist-info/METADATA
JustCause-0.4.dist-info/WHEEL
JustCause-0.4.dist-info/top_level.txt
JustCause-0.4.dist-info/RECORD
