Metadata-Version: 2.1
Name: JustCause
Version: 0.4
Summary: Comparing methods for causality analysis in a fair and just way.
Home-page: https://github.com/inovex/justcause/
Author: Maximilian Franz, Florian Wilhelm
Author-email: Maximilian.Franz@inovex.de, Florian.Wilhelm@inovex.de
License: mit
Project-URL: Documentation, https://justcause.readthedocs.io/
Platform: any
Classifier: Development Status :: 4 - Beta
Classifier: Programming Language :: Python
Classifier: Programming Language :: Python :: 3
Classifier: Programming Language :: Python :: 3 :: Only
Classifier: Programming Language :: Python :: 3.6
Classifier: Programming Language :: Python :: 3.7
Classifier: Programming Language :: Python :: 3.8
Classifier: Topic :: Software Development :: Libraries :: Python Modules
Classifier: Topic :: Scientific/Engineering :: Mathematics
Classifier: Operating System :: OS Independent
Classifier: License :: OSI Approved :: MIT License
Classifier: Intended Audience :: Developers
Classifier: Intended Audience :: Science/Research
Requires-Python: >=3.6
Requires-Dist: numpy
Requires-Dist: pyarrow
Requires-Dist: pandas (>=1.0)
Requires-Dist: scikit-learn
Requires-Dist: requests
Requires-Dist: pygam
Provides-Extra: testing
Requires-Dist: pytest ; extra == 'testing'
Requires-Dist: pytest-cov ; extra == 'testing'
